IcarusVerilog_HW/full_adder.v
module full_adder(input In1, In2, Cin, output Sum, Cout);

  assign Sum = (In1 ^ In2) ^ Cin;

  assign Cout = (In1 & In2) | (In2 & Cin) | (Cin & In1);

endmodule

IcarusVerilog_HW/full_adder_tb.v
module full_adder_tb;
  reg Cin, In1, In2;
  wire Cout, sum;
  full_adder uut ( .In1(In1), .In2(In2), .Cin(Cin), .Sum(Sum), .Cout(Cout));

  initial begin
    $dumpfile("full_adder.vcd");
    $dumpvars(0, full_adder_tb);
    $display("time\tCin\tIn1\tIn2\tCout\tSum");
    $monitor("%2d\t%b\t%b\t%b\t%b\t%b", $time, Cin, In1, In2, Cout, Sum);
    Cin = 0; In1 = 0; In2 = 0;
    #10 In1 = 1;
    #10 In2 = 1; In1 = 0;
    #10 In1 = 1;
    #10 Cin = 1; In2 = 0; In1 = 0;
    #10 In1 = 1;
    #10 In2 = 1; In1 = 0;
    #10 In1 = 1;
    #10 $finish;
  end
endmodule

IcarusVerilog_HW/full_adder.vcd
$date
	Sat Nov 12 12:04:18 2022
$end
$version
	Icarus Verilog
$end
$timescale
	1s
$end
$scope module full_adder_tb $end
$var wire 1 ! Sum $end
$var wire 1 " Cout $end
$var reg 1 # Cin $end
$var reg 1 $ In1 $end
$var reg 1 % In2 $end
$scope module uut $end
$var wire 1 # Cin $end
$var wire 1 " Cout $end
$var wire 1 $ In1 $end
$var wire 1 % In2 $end
$var wire 1 ! Sum $end
$upscope $end
$upscope $end
$enddefinitions $end
#0
$dumpvars
0%
0$
0#
0"
0!
$end
#10
1!
1$
#20
0$
1%
#30
1"
0!
1$
#40
0"
1!
0$
0%
1#
#50
0!
1"
1$
#60
0$
1%
#70
1!
1$
